oauth4cli/__init__.py
oauth4cli/example.py
oauth4cli/oauthSessionHelper.py
oauth4cli-0.3.1.dist-info/LICENSE
oauth4cli-0.3.1.dist-info/METADATA
oauth4cli-0.3.1.dist-info/WHEEL
oauth4cli-0.3.1.dist-info/top_level.txt
oauth4cli-0.3.1.dist-info/RECORD
