Metadata-Version: 2.1
Name: oauth4cli
Version: 0.3.1
Summary: A solution for an authorization code flow via Browser for the CLI.
Home-page: https://github.com/aruehl/oauth4cli
Author: Andreas Rühl
Author-email: Andreas Rühl <andreas.ruehl@gmail.com>
License: MIT License        
Classifier: Programming Language :: Python :: 3
Classifier: License :: OSI Approved :: MIT License
Classifier: Operating System :: OS Independent
Requires-Python: >=3.7
License-File: LICENSE
Requires-Dist: flask
Requires-Dist: requests
Requires-Dist: requests-oauthlib
Requires-Dist: werkzeug
